fancyconsole/__init__.py
fancyconsole-0.0.1.dist-info/LICENSE
fancyconsole-0.0.1.dist-info/METADATA
fancyconsole-0.0.1.dist-info/WHEEL
fancyconsole-0.0.1.dist-info/top_level.txt
fancyconsole-0.0.1.dist-info/RECORD
