Metadata-Version: 2.1
Name: fancyconsole
Version: 0.0.1
Summary: fancy console with colors
Home-page: https://pypi.org/project/fancyconsole/
Author: Alexander Pfefferle
Author-email: alex@pfefferle.xyz
License: UNKNOWN
Platform: UNKNOWN
Classifier: Programming Language :: Python :: 3
Classifier: License :: OSI Approved :: MIT License
